{
  "unversionedId": "Workout/plan",
  "id": "Workout/plan",
  "title": "Current Workout Plan",
  "description": "| Workout Name    | Sets     | Reps    | Comments    |",
  "source": "@site/docs/Workout/plan.md",
  "sourceDirName": "Workout",
  "slug": "/Workout/plan",
  "permalink": "/Workout/plan",
  "draft": false,
  "tags": [],
  "version": "current",
  "frontMatter": {
    "title": "Current Workout Plan"
  },
  "sidebar": "myAutogeneratedSidebar",
  "previous": {
    "title": "Priority vs Severity",
    "permalink": "/Testing-Concepts/Verification-vs-Validation"
  },
  "next": {
    "title": "Xray Intro",
    "permalink": "/Xray/"
  }
}