{
  "unversionedId": "AutomationFramework/Maven",
  "id": "AutomationFramework/Maven",
  "title": "Maven",
  "description": "POM(Project Object Model)",
  "source": "@site/docs/AutomationFramework/Maven.md",
  "sourceDirName": "AutomationFramework",
  "slug": "/AutomationFramework/Maven",
  "permalink": "/AutomationFramework/Maven",
  "draft": false,
  "tags": [],
  "version": "current",
  "frontMatter": {
    "title": "Maven"
  },
  "sidebar": "myAutogeneratedSidebar",
  "previous": {
    "title": "Grid",
    "permalink": "/AutomationFramework/Grid"
  },
  "next": {
    "title": "Log4J",
    "permalink": "/AutomationFramework/Log4J"
  }
}