{
  "unversionedId": "Zephyr/Zephyr",
  "id": "Zephyr/Zephyr",
  "title": "Zephyr Intro",
  "description": "Basics",
  "source": "@site/docs/Zephyr/Zephyr.md",
  "sourceDirName": "Zephyr",
  "slug": "/Zephyr/",
  "permalink": "/Zephyr/",
  "draft": false,
  "tags": [],
  "version": "current",
  "frontMatter": {
    "title": "Zephyr Intro"
  },
  "sidebar": "myAutogeneratedSidebar",
  "previous": {
    "title": "Xray",
    "permalink": "/Xray"
  },
  "next": {
    "title": "API",
    "permalink": "/static/API"
  }
}