{
  "label": "excalidraw",
  "permalink": "/tags/excalidraw",
  "allTagsPath": "/tags",
  "count": 5,
  "items": [
    {
      "id": "static/API",
      "title": "API",
      "description": "==⚠  Switch to EXCALIDRAW VIEW in the MORE OPTIONS menu of this document. ⚠==",
      "permalink": "/static/API"
    },
    {
      "id": "static/APITesting",
      "title": "APITesting",
      "description": "==⚠  Switch to EXCALIDRAW VIEW in the MORE OPTIONS menu of this document. ⚠==",
      "permalink": "/static/APITesting"
    },
    {
      "id": "static/SeleniumExcalidraw",
      "title": "SeleniumExcalidraw",
      "description": "==⚠  Switch to EXCALIDRAW VIEW in the MORE OPTIONS menu of this document. ⚠==",
      "permalink": "/static/SeleniumExcalidraw"
    },
    {
      "id": "static/SoapUI",
      "title": "SoapUI",
      "description": "==⚠  Switch to EXCALIDRAW VIEW in the MORE OPTIONS menu of this document. ⚠==",
      "permalink": "/static/SoapUI"
    },
    {
      "id": "static/Xray",
      "title": "Xray",
      "description": "==⚠  Switch to EXCALIDRAW VIEW in the MORE OPTIONS menu of this document. ⚠==",
      "permalink": "/static/Xray"
    }
  ]
}